mckinseysolvegame/__init__.py
mckinseysolvegame/_version.py
mckinseysolvegame/domain/__init__.py
mckinseysolvegame/domain/models.py
mckinseysolvegame/domain/services/__init__.py
mckinseysolvegame/domain/services/optimization_service.py
mckinseysolvegame/tests/__init__.py
mckinseysolvegame/tests/test_models.py
mckinseysolvegame/tests/test_optimization_service.py
mckinseysolvegame-1.1.4.dist-info/METADATA
mckinseysolvegame-1.1.4.dist-info/WHEEL
mckinseysolvegame-1.1.4.dist-info/top_level.txt
mckinseysolvegame-1.1.4.dist-info/RECORD
