Metadata-Version: 2.4
Name: mckinseysolvegame
Version: 1.1.4
Summary: Python library for solving the McKinsey Solve Game
Home-page: https://github.com/SebastienEveno/mckinseysolvegame
Author: Sebastien Eveno
Author-email: sebastien.louis.eveno@gmail.com
License: MIT
Classifier: Development Status :: 5 - Production/Stable
Classifier: Intended Audience :: Developers
Classifier: License :: OSI Approved :: MIT License
Classifier: Programming Language :: Python :: 3.10
Classifier: Operating System :: OS Independent
Classifier: Intended Audience :: Science/Research
Classifier: Topic :: Software Development
Classifier: Topic :: Scientific/Engineering :: Information Analysis
Requires-Python: >=3.10.2, <4
Requires-Dist: numpy>=1.23.5
Requires-Dist: pandas>=1.5.1
Requires-Dist: scipy>=1.9.3
Requires-Dist: pytest>=7.1.3
Requires-Dist: marshmallow>=3.19.0
Dynamic: author
Dynamic: author-email
Dynamic: classifier
Dynamic: description
Dynamic: description-content-type
Dynamic: home-page
Dynamic: license
Dynamic: requires-dist
Dynamic: requires-python
Dynamic: summary
